LICENSE.md
MANIFEST.in
README.md
setup.py
./cloudmesh/__init__.py
./cloudmesh/cloud_mesh_db.py
./cloudmesh/cloudmesh.py
./cloudmesh/cloudmesh_cloud.py
./cloudmesh/cloudmesh_new.py
./cloudmesh/cm_config.py
./cloudmesh/cm_keys.py
./cloudmesh/cm_mongodb.py
./cloudmesh/cm_projects.py
./cloudmesh/cm_rc.py
./cloudmesh/cm_shell.py
./cloudmesh/ldap_user.py
./cloudmesh/mock_cloud.py
./cloudmesh/mock_keystone.py
./cloudmesh/mock_user.py
./cloudmesh/mongodb.py
./cloudmesh/openstack_grizzly_cloud.py
./cloudmesh/test_cloudmesh.py
./cloudmesh/test_cm_config.py
./cloudmesh/test_cm_keys.py
./cloudmesh/util.py
./cloudmesh/azure/__init__.py
./cloudmesh/azure/cm_azure.py
./cloudmesh/azure/fabfile.py
./cloudmesh/eucalyptus/__init__.py
./cloudmesh/eucalyptus/eucalyptus.py
./cloudmesh/eucalyptus/eucalyptus_libcloud.py
./cloudmesh/eucalyptus/eucalyptus_new.py
./cloudmesh/openstack/__init__.py
./cloudmesh/openstack/cm_compute.py
./cloudmesh/openstack/cm_compute_old.py
./cloudmesh/openstack/cm_credential.py
./cloudmesh/openstack/cm_table.py
./cloudmesh/openstack/test_cm_compute.py
./cloudmesh/plugins/__init__.py
./cloudmesh/plugins/metrics.py
./flask_cm/__init__.py
./flask_cm/server.py
./flask_cm/server_new.py
flask_cm.egg-info/PKG-INFO
flask_cm.egg-info/SOURCES.txt
flask_cm.egg-info/dependency_links.txt
flask_cm.egg-info/entry_points.txt
flask_cm.egg-info/not-zip-safe
flask_cm.egg-info/requires.txt
flask_cm.egg-info/top_level.txt
flask_cm/static/css/bootstrap-responsive.css
flask_cm/static/css/bootstrap-responsive.min.css
flask_cm/static/css/bootstrap.css
flask_cm/static/css/bootstrap.min.css
flask_cm/static/css/datepicker.css
flask_cm/static/css/table.css
flask_cm/static/img/fg-logo-md-litejazz.png
flask_cm/static/img/fg-logo-white-24x36.png
flask_cm/static/img/fg-logo-white.png
flask_cm/static/img/glyphicons-halflings-white.png
flask_cm/static/img/glyphicons-halflings.png
flask_cm/static/img/hadoop-elephant.jpg
flask_cm/static/img/hadoop-microsoft.jpg
flask_cm/static/img/images.jpg
flask_cm/static/img/useful.txt
flask_cm/static/img/icons/png/.DS_Store
flask_cm/static/img/icons/png/_readme_first.txt
flask_cm/static/img/icons/png/glyphicons_000_glass.png
flask_cm/static/img/icons/png/glyphicons_001_leaf.png
