Metadata-Version: 1.0
Name: flask-cm
Version: 0.8.1
Summary: Cloud Mesh: managing multiple virtual machines in Clouds
Home-page: https://github.com/futuregrid/flask_cm
Author: Gregor von Laszewski
Author-email: laszewski@gmail.com
License: Apache 2.0
Keywords: Cloud FutureGrid Flask farmework
Platform: UNKNOWN
Classifier: Intended Audience :: Developers
Classifier: Intended Audience :: Education
Classifier: Intended Audience :: Science/Research
Classifier: Development Status :: 4 - Beta
Classifier: Intended Audience :: Developers
Classifier: License :: OSI Approved :: Apache Software License
Classifier: Programming Language :: Python
Classifier: Topic :: Database
Classifier: Topic :: Software Development :: Libraries :: Python Modules
Classifier: Operating System :: POSIX :: Linux
Classifier: Programming Language :: Python :: 2.7
Classifier: Operating System :: MacOS :: MacOS X
Classifier: Topic :: Scientific/Engineering
Classifier: Topic :: System :: Clustering
Classifier: Topic :: System :: Distributed Computing
